mcpulse/__init__.py
mcpulse/_convert.py
mcpulse/client.py
mcpulse/collector.py
mcpulse/config.py
mcpulse/query.py
mcpulse/sanitizer.py
mcpulse/tracker.py
mcpulse/types.py
mcpulse/pb/analytics_pb2.py
mcpulse/pb/analytics_pb2_grpc.py
mcpulse-0.1.0.dist-info/METADATA
mcpulse-0.1.0.dist-info/WHEEL
mcpulse-0.1.0.dist-info/RECORD
