Metadata-Version: 2.4
Name: mcpulse
Version: 0.1.0
Summary: Official Python SDK for MCPulse - Analytics and observability for MCP servers
Project-URL: Homepage, https://github.com/sirrobot01/mcpulse
Project-URL: Documentation, https://docs.mcpulse.io
Project-URL: Repository, https://github.com/sirrobot01/mcpulse
Project-URL: Issues, https://github.com/sirrobot01/mcpulse/issues
Author-email: MCPulse Team <support@mcpulse.io>
License: Apache-2.0
Keywords: analytics,mcp,model-context-protocol,monitoring,observability,telemetry
Classifier: Development Status :: 4 - Beta
Classifier: Intended Audience :: Developers
Classifier: License :: OSI Approved :: Apache Software License
Classifier: Operating System :: OS Independent
Classifier: Programming Language :: Python
Classifier: Programming Language :: Python :: 3
Classifier: Programming Language :: Python :: 3.9
Classifier: Programming Language :: Python :: 3.10
Classifier: Programming Language :: Python :: 3.11
Classifier: Programming Language :: Python :: 3.12
Classifier: Topic :: Software Development :: Libraries :: Python Modules
Classifier: Topic :: System :: Monitoring
Requires-Python: >=3.10
Requires-Dist: grpcio-tools>=1.60.0
Requires-Dist: grpcio>=1.60.0
Requires-Dist: mcp>=1.16.0
Requires-Dist: protobuf>=4.25.0
Requires-Dist: pytest>=8.4.2
Provides-Extra: dev
Requires-Dist: black>=23.0.0; extra == 'dev'
Requires-Dist: grpcio-testing>=1.60.0; extra == 'dev'
Requires-Dist: mypy>=1.7.0; extra == 'dev'
Requires-Dist: pytest-asyncio>=0.21.0; extra == 'dev'
Requires-Dist: pytest-cov>=4.1.0; extra == 'dev'
Requires-Dist: pytest>=7.4.0; extra == 'dev'
Requires-Dist: ruff>=0.1.0; extra == 'dev'
Provides-Extra: mcp
Requires-Dist: mcp>=1.0.0; extra == 'mcp'
